{"image_index": 18417, "image_filename": "nil", "objects": [{"attributes": {"Aroma": 0.8, "Flavor": 0.69875, "Aftertaste": 0.71165, "Acidity": 0.76229, "Body": 0.75758, "Balance": 0.70514, "Uniformity": 0.8, "Clean-Cup": 0.8, "Sweetness": 0.8, "Moisture": 0.5, "altitude-mean-meters": 0.00762}, "description": {}}, {"attributes": {"Aroma": 0.88571, "Flavor": 0.87769, "Aftertaste": 0.86505, "Acidity": 0.89486, "Body": 0.88345, "Balance": 0.86629, "Uniformity": 1.0, "Clean-Cup": 1.0, "Sweetness": 1.0, "Moisture": 0.55, "altitude-mean-meters": 0.00593}, "description": {}}, {"attributes": {"Aroma": 0.87657, "Flavor": 0.85844, "Aftertaste": 0.87428, "Acidity": 0.88571, "Body": 0.89394, "Balance": 0.78057, "Uniformity": 1.0, "Clean-Cup": 1.0, "Sweetness": 1.0, "Moisture": 0.6, "altitude-mean-meters": 0.00604}, "description": {}}, {"attributes": {"Aroma": 0.76229, "Flavor": 0.73613, "Aftertaste": 0.71165, "Acidity": 0.76229, "Body": 0.79604, "Balance": 0.70514, "Uniformity": 0.8, "Clean-Cup": 0.8, "Sweetness": 0.8, "Moisture": 0.5, "altitude-mean-meters": 0.00762}, "description": {}}]}